{
  "ngDeps": {
    "1": "",
    "3": [
      {
        "1": "package:angular2/core.dart",
        "5": false
      },
      {
        "1": "package:angular2/router.dart",
        "5": false
      },
      {
        "1": "hero_service.dart",
        "5": false
      },
      {
        "1": "heroes_component.dart",
        "5": false
      }
    ],
    "5": [
      {
        "1": "Bogus",
        "7": [
          {
            "2": "HeroesComponent"
          }
        ]
      },
      {
        "1": "AppComponent",
        "4": [
          {
            "1": "RouteConfig",
            "2": [
              "const [const Route(path: '/heroes', name: 'Heroes', component: HeroesComponent)]"
            ],
            "4": false
          }
        ],
        "7": [
          {
            "2": "ROUTER_DIRECTIVES"
          }
        ]
      }
    ],
    "6": "app_component_1.dart"
  },
  "type": {
    "Bogus": {
      "class": "Directive",
      "isComponent": true,
      "selector": "my-app",
      "exportAs": null,
      "type": {
        "class": "Type",
        "name": "Bogus",
        "moduleUrl": "asset:angular2_tour_of_heroes/lib/app_component_1.dart",
        "prefix": null,
        "isHost": false,
        "value": null,
        "diDeps": []
      },
      "changeDetection": 5,
      "inputs": {},
      "outputs": {},
      "hostListeners": {},
      "hostProperties": {},
      "hostAttributes": {},
      "lifecycleHooks": [],
      "template": {
        "encapsulation": 2,
        "template": "      <h1>{{title}}</h1>\n      <my-heroes></my-heroes>",
        "templateUrl": "asset:angular2_tour_of_heroes/lib/app_component_1.dart",
        "styles": [],
        "styleUrls": [],
        "ngContentSelectors": []
      },
      "providers": [
        {
          "class": "Identifier",
          "name": "HeroService",
          "moduleUrl": null,
          "prefix": null,
          "value": null
        }
      ],
      "viewProviders": [],
      "queries": [],
      "viewQueries": []
    },
    "AppComponent": {
      "class": "Directive",
      "isComponent": true,
      "selector": "my-app",
      "exportAs": null,
      "type": {
        "class": "Type",
        "name": "AppComponent",
        "moduleUrl": "asset:angular2_tour_of_heroes/lib/app_component_1.dart",
        "prefix": null,
        "isHost": false,
        "value": null,
        "diDeps": []
      },
      "changeDetection": 5,
      "inputs": {},
      "outputs": {},
      "hostListeners": {},
      "hostProperties": {},
      "hostAttributes": {},
      "lifecycleHooks": [],
      "template": {
        "encapsulation": 2,
        "template": "      <h1>{{title}}</h1>\n      <a [routerLink]=\"['Heroes']\">Heroes</a>\n      <router-outlet></router-outlet>",
        "templateUrl": "asset:angular2_tour_of_heroes/lib/app_component_1.dart",
        "styles": [],
        "styleUrls": [],
        "ngContentSelectors": []
      },
      "providers": [
        {
          "class": "Identifier",
          "name": "HeroService",
          "moduleUrl": null,
          "prefix": null,
          "value": null
        },
        {
          "class": "Identifier",
          "name": "ROUTER_PROVIDERS",
          "moduleUrl": null,
          "prefix": null,
          "value": null
        }
      ],
      "viewProviders": [],
      "queries": [],
      "viewQueries": []
    }
  },
  "alias": {}
}